algomodule/keccak.c
algomodule/bitblock.cpython-39-darwin.so
algomodule/twe.cpython-39-darwin.so
algomodule/x15.c
algomodule/x11.c
algomodule/skein.pyx
algomodule/groestl.pyx
algomodule/meraki.cpp
algomodule/quark.cpython-39-darwin.so
algomodule/scrypt.pyx
algomodule/keccak.pyx
algomodule/dcrypt.c
algomodule/blake.pyx
algomodule/x11.cpython-39-darwin.so
algomodule/qubit.c
algomodule/fugue.pyx
algomodule/x14.cpython-39-darwin.so
algomodule/hefty1.c
algomodule/blake.c
algomodule/hefty1.pyx
algomodule/fresh.pyx
algomodule/fugue.cpython-39-darwin.so
algomodule/shavite3.c
algomodule/hefty1.cpython-39-darwin.so
algomodule/meraki.cpython-39-darwin.so
algomodule/twe.c
algomodule/dcrypt.cpython-39-darwin.so
algomodule/__init__.py
algomodule/bcrypt.c
algomodule/x15.cpython-39-darwin.so
algomodule/fresh.c
algomodule/threes.pyx
algomodule/threes.cpython-39-darwin.so
algomodule/keccak.cpython-39-darwin.so
algomodule/jackpot.c
algomodule/qubit.cpython-39-darwin.so
algomodule/x17.c
algomodule/x16rv2.pyx
algomodule/bitblock.c
algomodule/fugue.c
algomodule/twe.pyx
algomodule/fresh.cpython-39-darwin.so
algomodule/groestl.c
algomodule/scrypt.c
algomodule/bitblock.pyx
algomodule/x13.cpython-39-darwin.so
algomodule/blake.cpython-39-darwin.so
algomodule/x13.c
algomodule/bcrypt.cpython-39-darwin.so
algomodule/jackpot.cpython-39-darwin.so
algomodule/x16rv2.c
algomodule/qubit.pyx
algomodule/nist5.cpython-39-darwin.so
algomodule/dcrypt.pyx
algomodule/groestl.cpython-39-darwin.so
algomodule/quark.c
algomodule/neoscrypt.c
algomodule/x17.cpython-39-darwin.so
algomodule/skein.cpython-39-darwin.so
algomodule/x14.c
algomodule/x17.pyx
algomodule/x15.pyx
algomodule/shavite3.cpython-39-darwin.so
algomodule/neoscrypt.cpython-39-darwin.so
algomodule/bcrypt.pyx
algomodule/nist5.pyx
algomodule/skein.c
algomodule/shavite3.pyx
algomodule/x14.pyx
algomodule/x16rv2.cpython-39-darwin.so
algomodule/nist5.c
algomodule/threes.c
algomodule-2.0.0.dist-info/RECORD
algomodule-2.0.0.dist-info/WHEEL
algomodule-2.0.0.dist-info/top_level.txt
algomodule-2.0.0.dist-info/METADATA
