Metadata-Version: 2.1
Name: algomodule
Version: 2.0.0
Summary: CryptoCurrency Hashing Library
Home-page: https://github.com/electrum-altcoin/algomodule
Author: Ahmed Bodiwala
Author-email: ahmedbodi@crypto-expert.com
License: MIT
Project-URL: Code, https://github.com/electrum-altcoin/AlgoLib
Project-URL: Issue tracker, https://github.com/electrum-altcoin/AlgoLib/issues
Platform: UNKNOWN
Classifier: Development Status :: 1 - Planning
Classifier: License :: OSI Approved :: MIT License
Classifier: Natural Language :: English
Classifier: Operating System :: OS Independent
Classifier: Programming Language :: C
Classifier: Programming Language :: Cython
Classifier: Programming Language :: Python
Classifier: Programming Language :: Python :: 3
Classifier: Programming Language :: Python :: 3.4
Classifier: Programming Language :: Python :: 3.5
Classifier: Programming Language :: Python :: 3.6
Classifier: Programming Language :: Python :: 3.7
Classifier: Programming Language :: Python :: 3 :: Only
Classifier: Programming Language :: Python :: Implementation :: CPython
Requires-Python: >=2.6
